{
"WUPBS": "Once",
"POPB": "upon",
"AEU": "a",
"TAOEUPL": "time",
"THR": "there",
"WA": "was",
"AEU": "a",
"HREUL": "little",
"PWOEU": "boy",
"WHO": "who",
"H": "had",
"TAEPB": "taken",
"KOELD TP-PL": "cold.",
"E": "He",
"H": "had",
"TKWOPB": "gone",
"OUT": "out",
"SKP": "and",
"TKPWOT": "got",
"HEUS": "his",
"TPAOET": "feet",
"WET STPH*FPLT": "wet;",
"THOE": "though",
"TPHOEB": "nobody",
"KO": "could",
"PHAPBLG": "imagine",
"HOU": "how",
"T": "it",
"H": "had",
"HAPD KW-BG": "happened,",
"TPOR": "for",
"T": "it",
"WA": "was",
"KWAOEUT": "quite",
"TKRAOEU": "dry",
"WHR* TP-PL": "weather.",
"SO": "So",
"HEUS": "his",
"PHOER": "mother",
"UPB/TKRES/-D": "undressed",
"HEUPL KW-BG": "him,",
"PUT": "put",
"HEUPL": "him",
"TO": "to",
"PWED KW-BG": "bed,",
"SKP": "and",
"H": "had",
"-T": "the",
"TAE H-PB POT": "tea-pot",
"PWRAUT": "brought",
"TPH KW-BG": "in,",
"TO": "to",
"PHAEUBG": "make",
"HEUPL": "him",
"AEU": "a",
"TKPWAOD": "good",
"KUP": "cup",
"-F": "of",
"XXX Elderflower": "Elderflower",
"TAE TP-PL": "tea.",
"SKWRUFT": "Just",
"AT": "at",
"THA": "that",
"PHOEPLT": "moment",
"-T": "the",
"PHER/REU": "merry",
"OLD": "old",
"PHAPB": "man",
"KAEUPL": "came",
"TPH": "in",
"WHO": "who",
"HREUFD": "lived",
"UP": "up",
"AEU H-PB TOP": "a-top",
"-F": "of",
"-T": "the",
"HOUS": "house",
"AUL": "all",
"A/HROEPB STPH*FPLT": "alone;",
"TPOR": "for",
"E": "he",
"H": "had",
"TPHAOERT": "neither",
"WAOEUF": "wife",
"TPH-R": "nor",
"KHEURPB H-PB H-PB PWUT": "children--but",
"E": "he",
"HRAOEUBGD": "liked",
"KHEURPB": "children",
"SRE": "very",
"PHUFP KW-BG": "much,",
"SKP": "and",
"TPHAOU": "knew",
"SO": "so",
"PHAEPB": "many",
"TPAEUR/REU": "fairy",
"TAELS KW-BG": "tales,",
"THA": "that",
"T": "it",
"WA": "was",
"KWAOEUT": "quite",
"TKHRAOEUT/-FL TP-PL": "delightful.",
"KR-GS TPHOU": "\"Now",
"TKREU": "drink",
"KWROUR": "your",
"TAE KW-BG KR-GS": "tea,\"",
"SAEUD": "said",
"-T": "the",
"PWOEU AE S*/SP-S": "boy's",
"PHOER STPH*FPLT": "mother;",
"KR-GS THEPB KW-BG": "\"then,",
"PRAPS KW-BG": "perhaps,",
"U": "you",
"PHAE": "may",
"HAER": "hear",
"AEU": "a",
"TPAEUR/REU": "fairy",
"TAEL TP-PL KR-GS": "tale.\"",
"KR-GS TP": "\"If",
"EU": "I",
"H": "had",
"PWUT": "but",
"S-G": "something",
"TPHU": "new",
"TO": "to",
"TEL KW-BG KR-GS": "tell,\"",
"SAEUD": "said",
"-T": "the",
"OLD": "old",
"PHAPB TP-PL": "man.",
"KR-GS PWUT": "\"But",
"HOU": "how",
"TK": "did",
"-T": "the",
"KHAOEULD": "child",
"TKPWET": "get",
"HEUS": "his",
"TPAOET": "feet",
"WET H-F KR-GS": "wet?\"",
"KR-GS THA": "\"That",
"S": "is",
"-T": "the",
"SRE": "very",
"THEUPBG": "thing",
"THA": "that",
"TPHOEB": "nobody",
"K": "can",
"PHAEUBG": "make",
"OUT KW-BG KR-GS": "out,\"",
"SAEUD": "said",
"HEUS": "his",
"PHOER TP-PL": "mother.",
"KR-GS *PL": "\"Am",
"EU": "I",
"TO": "to",
"HAER": "hear",
"AEU": "a",
"TPAEUR/REU": "fairy",
"TAEL H-F KR-GS": "tale?\"",
"SK-D": "asked",
"-T": "the",
"HREUL": "little",
"PWOEU TP-PL": "boy.",
"KR-GS KWRE KW-BG": "\"Yes,",
"TP": "if",
"U": "you",
"K": "can",
"TEL": "tell",
"PHE": "me",
"ELG H-PB H-PB TPOR": "exactly--for",
"EU": "I",
"PHUFT": "must",
"TPHOE": "know",
"THA": "that",
"TPEURS H-PB H-PB HOU": "first--how",
"TKAOEP": "deep",
"-T": "the",
"TKPWOURT": "gutter",
"S": "is",
"TPH": "in",
"-T": "the",
"HREUL": "little",
"STRAOET": "street",
"OP/SEUT KW-BG": "opposite,",
"THA": "that",
"U": "you",
"PAS": "pass",
"THRU": "through",
"TPH": "in",
"TKPW-G": "going",
"TO": "to",
"SKAOL TP-PL KR-GS": "school.\"",
"KR-GS SKWRUFT": "\"Just",
"UP": "up",
"TO": "to",
"-T": "the",
"PH*EULD": "middle",
"-F": "of",
"PHEU": "my",
"PWAOT KW-BG KR-GS": "boot,\""
}
