{
"AT": "at",
"KR-GS SREUFT/-G KW-BG KR-GS": "\"Visiting,\"",
"W": "with",
"-T": "the",
"HRA*EDZ": "ladies",
"-F": "of",
"-T": "the",
"KORT STPH*FPLT": "court;",
"SKP": "and",
"WHEPB": "when",
"SHE": "she",
"SAU": "saw",
"-T": "the",
"KAS/KETS": "caskets",
"W": "with",
"-T": "the",
"PREPBTS KW-BG": "presents,",
"SHE": "she",
"KHRAP/-D": "clapped",
"HER": "her",
"HAPBDZ": "hands",
"TPOR": "for",
"SKWROEU TP-PL": "joy.",
"KR-GS HA*E KW-BG": "\"Ah,",
"TP": "if",
"T": "it",
"WR": "were",
"PWUT": "but",
"AEU": "a",
"HREUL": "little",
"PUS/SEU H-PB KAT SKHRAPL KR-GS": "pussy-cat!\"",
"SAEUD": "said",
"SHE STPH*FPLT": "she;",
"PWUT": "but",
"-T": "the",
"ROES": "rose",
"TRAOE KW-BG": "tree,",
"W": "with",
"EUTS": "its",
"PWAOUFL": "beautiful",
"ROES": "rose",
"KAEUPL": "came",
"TO": "to",
"SRAOU TP-PL": "view.",
"KR-GS O*ERBGS KW-BG": "\"Oh,",
"HOU": "how",
"PRET/HREU": "prettily",
"T": "it",
"S": "is",
"PHAED SKHRAPL KR-GS": "made!\"",
"SAEUD": "said",
"AUL": "all",
"-T": "the",
"KORT": "court",
"HRA*EDZ TP-PL": "ladies.",
"KR-GS T": "\"It",
"S": "is",
"PHOR": "more",
"THAPB": "than",
"PREUT KW-BG KR-GS": "pretty,\"",
"SAEUD": "said",
"-T": "the",
"EPL/ROR KW-BG": "Emperor,",
"KR-GS T": "\"it",
"S": "is",
"KHARPL/-G SKHRAPL KR-GS": "charming!\"",
"PWUT": "But",
"-T": "the",
"PREUPB/ES": "Princess",
"TUFPD": "touched",
"T KW-BG": "it,",
"SKP": "and",
"WA": "was",
"HR-PL": "almost",
"R*ED": "ready",
"TO": "to",
"KRAOEU TP-PL": "cry.",
"KR-GS XXX Fie KW-BG": "\"Fie,",
"PA/PA SKHRAPL KR-GS": "papa!\"",
"SAEUD": "said",
"SHE TP-PL": "she.",
"KR-GS T": "\"It",
"S": "is",
"TPHOT": "not",
"PHAED": "made",
"AT": "at",
"AUL KW-BG": "all,",
"T": "it",
"S": "is",
"TPHARL SKHRAPL KR-GS": "natural!\"",
"KR-GS HRET": "\"Let",
"US": "us",
"SAOE": "see",
"WHA": "what",
"S": "is",
"TPH": "in",
"-T": "the",
"OER": "other",
"KAFBGT KW-BG": "casket,",
"PW-F": "before",
"WE": "we",
"TKPWET": "get",
"TPHAO": "into",
"AEU": "a",
"PWAD": "bad",
"HAOURPL KW-BG KR-GS": "humor,\"",
"SAEUD": "said",
"-T": "the",
"EPL/ROR TP-PL": "Emperor.",
"SO": "So",
"-T": "the",
"TPHAOEUT/-G/TKPWAEL": "nightingale",
"KAEUPL": "came",
"TPO*RT": "forth",
"SKP": "and",
"SAPBG": "sang",
"SO": "so",
"TKHRAOEUT/-FL/HREU": "delightfully",
"THA": "that",
"AT": "at",
"TPEURS": "first",
"TPHO": "no",
"WUPB": "one",
"KO": "could",
"SAEU": "say",
"TPHEUG": "anything",
"EUL H-PB HAOURPL/-D": "ill-humored",
"-F": "of",
"HER TP-PL": "her.",
"KR-GS XXX Superbe SKHRAPL": "\"Superbe!",
"XXX Charmant SKHRAPL KR-GS": "Charmant!\"",
"SKHRAEUPL/-D": "exclaimed",
"-T": "the",
"HRA*EDZ STPH*FPLT": "ladies;",
"TPOR": "for",
"THE": "they",
"AUL": "all",
"AOUFD": "used",
"TO": "to",
"KHAT/ER": "chatter",
"TPREFPB KW-BG": "French,",
"AOEFP": "each",
"WUPB": "one",
"WORS": "worse",
"THAPB": "than",
"HER": "her",
"TPHAEUB TP-PL": "neighbor.",
"KR-GS HOU": "\"How",
"PHUFP": "much",
"-T": "the",
"PWEURD": "bird",
"RAO*EUPBDZ": "reminds",
"PHE": "me",
"-F": "of",
"-T": "the",
"PHAO*UL": "musical",
"PWOBGS": "box",
"THA": "that",
"PWHROPBGD": "belonged",
"TO": "to",
"OUR": "our",
"PWHR*EFD": "blessed",
"*EPL/RES KW-BG KR-GS": "Empress,\"",
"SAEUD": "said",
"APB": "an",
"OLD": "old",
"TPHAO*EUT TP-PL": "knight.",
"KR-GS O*ERBGS": "\"Oh",
"KWRE SKHRAPL": "yes!",
"THEZ": "These",
"R": "are",
"-T": "the",
"SAEUPL": "same",
"TOEPBS KW-BG": "tones,",
"-T": "the",
"SAEUPL": "same",
"SKAOUGS TP-PL KR-GS": "execution.\"",
"KR-GS KWRE SKHRAPL": "\"Yes!",
"KWRE SKHRAPL KR-GS": "yes!\"",
"SAEUD": "said",
"-T": "the",
"EPL/ROR KW-BG": "Emperor,",
"SKP": "and",
"E": "he",
"WEPT": "wept",
"HRAOEUBG": "like",
"AEU": "a",
"KHAOEULD": "child",
"AT": "at",
"-T": "the",
"RERPBS TP-PL": "remembrance.",
"KR-GS EU": "\"I",
"HR": "will",
"STEUL": "still",
"HOEP": "hope",
"THA": "that",
"T": "it",
"S": "is",
"TPHOT": "not",
"AEU": "a"
}
