{
"XXX Gerda": "Gerda",
"PWEU": "by",
"-T": "the",
"HAPBD KW-BG": "hand,",
"HRED": "led",
"HER": "her",
"TPHAO": "into",
"-T": "the",
"HREUL": "little",
"KOT/APBLG KW-BG": "cottage,",
"SKP": "and",
"HROBGD": "locked",
"-T": "the",
"TKAOR TP-PL": "door.",
"-T": "The",
"WO*EUPBDZ": "windows",
"WR": "were",
"SRE": "very",
"HAOEU": "high",
"UP STPH*FPLT": "up;",
"-T": "the",
"TKPWHRAS": "glass",
"WA": "was",
"RED KW-BG": "red,",
"PWHRU KW-BG": "blue,",
"SKP": "and",
"TKPWRAOEPB KW-BG": "green,",
"SKP": "and",
"-T": "the",
"SULGT": "sunlight",
"SHO*EPB": "shone",
"THRU": "through",
"KWAOEUT": "quite",
"WOPBD/ROUS/HREU": "wondrously",
"TPH": "in",
"AUL": "all",
"SORTS": "sorts",
"-F": "of",
"KHRORS TP-PL": "colors.",
"OPB": "On",
"-T": "the",
"TAEUBL": "table",
"STAOD": "stood",
"-T": "the",
"PHO*S": "most",
"EBGS/KWEUFT": "exquisite",
"KHER/REU/KWREU/-S KW-BG": "cherries,",
"SKP": "and",
"XXX Gerda": "Gerda",
"AEUT": "ate",
"AZ": "as",
"PHAEPB": "many",
"AZ": "as",
"SHE": "she",
"KHOES KW-BG": "chose,",
"TPOR": "for",
"SHE": "she",
"H": "had",
"PERPLGS": "permission",
"TO": "to",
"TKO": "do",
"SO TP-PL": "so.",
"WHAOEUL": "While",
"SHE": "she",
"WA": "was",
"AOEGT KW-BG": "eating,",
"-T": "the",
"OLD": "old",
"WOPL": "woman",
"KOEPLD": "combed",
"HER": "her",
"HAEUR": "hair",
"W": "with",
"AEU": "a",
"TKOELD/*EPB": "golden",
"KOEPL KW-BG": "comb,",
"SKP": "and",
"HER": "her",
"HAEUR": "hair",
"KURLD": "curled",
"SKP": "and",
"SHO*EPB": "shone",
"W": "with",
"AEU": "a",
"HROFL": "lovely",
"TKOELD/*EPB": "golden",
"KROR": "color",
"ARPBD": "around",
"THA": "that",
"SWAOET": "sweet",
"HREUL": "little",
"TPAEUS KW-BG": "face,",
"WEU": "which",
"WA": "was",
"SO": "so",
"ROUPBD": "round",
"SKP": "and",
"SO": "so",
"HRAOEUBG": "like",
"AEU": "a",
"ROES TP-PL": "rose.",
"KR-GS EU": "\"I",
"SR": "have",
"OFPB": "often",
"HROPBG/-D": "longed",
"TPOR": "for",
"SUFP": "such",
"AEU": "a",
"TKAER": "dear",
"HREUL": "little",
"TKPWEURL KW-BG KR-GS": "girl,\"",
"SAEUD": "said",
"-T": "the",
"OLD": "old",
"WOPL TP-PL": "woman.",
"KR-GS TPHOU": "\"Now",
"U": "you",
"SHAL": "shall",
"SAOE": "see",
"HOU": "how",
"WEL": "well",
"WE": "we",
"TPWRAE": "agree",
"TOGT KR-GS STPH*FPLT": "together\";",
"SKP": "and",
"WHAOEUL": "while",
"SHE": "she",
"KOEPLD": "combed",
"HREUL": "little",
"XXX Gerda AE S*/SP-S": "Gerda's",
"HAEUR KW-BG": "hair,",
"-T": "the",
"KHAOEULD": "child",
"TPAURGT": "forgot",
"HER": "her",
"TPOFRT H-PB PWROER": "foster-brother",
"KAEU": "Kay",
"PHOR": "more",
"SKP": "and",
"PHOR KW-BG": "more,",
"TPOR": "for",
"-T": "the",
"OLD": "old",
"WOPL": "woman",
"*URPBD": "understood",
"PHA/SKWREUBG STPH*FPLT": "magic;",
"PWUT": "but",
"SHE": "she",
"WA": "was",
"TPHO": "no",
"AOEFL": "evil",
"-BG KW-BG": "being,",
"SHE": "she",
"OEPBL": "only",
"PRABG/TEUS/-D": "practised",
"WEUFP/KRAFT": "witchcraft",
"AEU": "a",
"HREUL": "little",
"TPOR": "for",
"HER": "her",
"OEPB": "own",
"PRAOEUFT": "private",
"A/PHAOUS/*PLT KW-BG": "amusement,",
"SKP": "and",
"TPHOU": "now",
"SHE": "she",
"WAPBTD": "wanted",
"SRE": "very",
"PHUFP": "much",
"TO": "to",
"KAOEP": "keep",
"HREUL": "little",
"XXX Gerda TP-PL": "Gerda.",
"SHE": "She",
"TH-FR": "therefore",
"WEPBT": "went",
"OUT": "out",
"TPH": "in",
"-T": "the",
"TKPWA*RPB KW-BG": "garden,",
"STREFPD": "stretched",
"OUT": "out",
"HER": "her",
"KRAOBGD": "crooked",
"STEUBG": "stick",
"TORDZ": "towards",
"-T": "the",
"ROES H-PB PWURBS KW-BG": "rose-bushes,",
"WEU KW-BG": "which,",
"PWAOUFL/HREU": "beautifully",
"AZ": "as",
"THE": "they",
"WR": "were",
"PWHROEG KW-BG": "blowing,",
"AUL": "all",
"SA*PBG": "sank",
"TPHAO": "into",
"-T": "the",
"*ERT": "earth",
"SKP": "and"
}
